sentinelsearcher/__init__.py
sentinelsearcher/config.py
sentinelsearcher/main.py
sentinelsearcher/providers.py
sentinelsearcher/py.typed
sentinelsearcher-0.2.0.dist-info/WHEEL
sentinelsearcher-0.2.0.dist-info/entry_points.txt
sentinelsearcher-0.2.0.dist-info/METADATA
sentinelsearcher-0.2.0.dist-info/RECORD
