Metadata-Version: 2.3
Name: sentinelsearcher
Version: 0.2.0
Summary: AI-powered web search and structured data extraction using Anthropic Claude or OpenAI GPT
Keywords: web-search,ai,anthropic,openai,claude,gpt,structured-data,web-scraping,automation
Author: Matheus Kunzler Maldaner
Author-email: Matheus Kunzler Maldaner <matheus@sisnema.com.br>
License: MIT
Classifier: Development Status :: 4 - Beta
Classifier: Intended Audience :: Developers
Classifier: License :: OSI Approved :: MIT License
Classifier: Operating System :: OS Independent
Classifier: Programming Language :: Python :: 3
Classifier: Programming Language :: Python :: 3.11
Classifier: Programming Language :: Python :: 3.12
Classifier: Programming Language :: Python :: 3.13
Classifier: Topic :: Internet :: WWW/HTTP
Classifier: Topic :: Scientific/Engineering :: Artificial Intelligence
Classifier: Typing :: Typed
Requires-Dist: anthropic>=0.72.0
Requires-Dist: python-dotenv>=1.2.1
Requires-Dist: pyyaml>=6.0.3
Requires-Dist: openai>=1.50.0 ; extra == 'all'
Requires-Dist: openai>=1.50.0 ; extra == 'openai'
Requires-Python: >=3.11
Project-URL: Documentation, https://github.com/matheusmaldaner/sentinelsearcher#readme
Project-URL: Homepage, https://github.com/matheusmaldaner/sentinelsearcher
Project-URL: Issues, https://github.com/matheusmaldaner/sentinelsearcher/issues
Project-URL: Repository, https://github.com/matheusmaldaner/sentinelsearcher
Provides-Extra: all
Provides-Extra: openai
